aller/__init__.py
aller-0.0.0.dist-info/METADATA
aller-0.0.0.dist-info/WHEEL
aller-0.0.0.dist-info/licenses/LICENSE
aller-0.0.0.dist-info/RECORD
