Metadata-Version: 2.3
Name: aller
Version: 0.0.0
Summary: A framework for composing concurrent applications
Project-URL: Source, https://github.com/davidbrochart/aller
Project-URL: Issues, https://github.com/davidbrochart/aller/issues
Author-email: David Brochart <david.brochart@gmail.com>
License: BSD 3-Clause License
Classifier: Development Status :: 4 - Beta
Classifier: Intended Audience :: Developers
Classifier: License :: OSI Approved :: BSD License
Classifier: Programming Language :: Python
Classifier: Programming Language :: Python :: 3
Classifier: Programming Language :: Python :: 3.9
Classifier: Programming Language :: Python :: 3.10
Classifier: Programming Language :: Python :: 3.11
Classifier: Programming Language :: Python :: 3.12
Classifier: Programming Language :: Python :: 3.13
Classifier: Typing :: Typed
Requires-Python: >=3.9
Requires-Dist: anyio
Provides-Extra: test
Requires-Dist: coverage[toml]<8,>=7; extra == 'test'
Requires-Dist: mypy; extra == 'test'
Requires-Dist: pytest<9,>=8; extra == 'test'
Requires-Dist: ruff; extra == 'test'
Requires-Dist: trio<0.28,>=0.27.0; extra == 'test'
